[
  {
    "avatar": "https://ddragon.leagueoflegends.com/cdn/img/champion/splash/Lux_0.jpg",
    "name": "Lux",
    "nickname": "Леди Сияния",
    "discription": "Пиздатая мадам с примитивными шутками, но сильной ультой!",
    "params": { "Agressive": true, "PersonClass": "mage" }
  },
  {
    "avatar": "",
    "name": "",
    "nickname": "",
    "discription": "",
    "params": { "Agressive": true, "PersonClass": "warrior" }
  },
  {
    "avatar": "",
    "name": "",
    "nickname": "",
    "discription": "",
    "params": { "Agressive": false, "PersonClass": "mage" }
  },
  {
    "avatar": "",
    "name": "",
    "nickname": "",
    "discription": "",
    "params": { "Agressive": false, "PersonClass": "karry" }
  }
]
